{
    "乐土刷级-接口层": {
        "post_delay": 0,
        "pre_delay": 0,
        "rate_limit": 0,
        "next": [
            "乐土刷级-减负模式-开始任务层"
        ]
    },
    "乐土刷级-减负模式-开始任务层": {
        "next": [
            "乐土刷级-减负模式-已进入女武神选择界面",
            "乐土刷级-减负模式-总任务层",
            "乐土刷级-减负模式-已进入往世乐土箱庭",
            "乐土刷级-减负模式-已进入深层序列选buff准备出击界面",
            "[JumpBack]启动并进入游戏"
        ]
    },
    "乐土刷级-减负模式-总任务层": {
        "roi": [
            896,
            273,
            270,
            297
        ],
        "recognition": "TemplateMatch",
        "template": [
            "主页UI/休伯利安主界面.png",
            "主页UI/休伯利安主界面绿幕.png"
        ],
        "green_mask": true,
        "next": [
            "乐土刷级-减负模式-已进入往世乐土箱庭",
            "[JumpBack]乐土刷级-减负模式-点击进入乐土刷级-减负模式",
            "[JumpBack]乐土刷级-减负模式-点击主菜单的出击",
            "[JumpBack]乐土刷级-减负模式-点击出击的挑战"
        ]
    },
    "乐土刷级-减负模式-点击主菜单的出击": {
        "roi": [
            1089,
            257,
            174,
            200
        ],
        "recognition": "OCR",
        "expected": [
            "出击"
        ],
        "action": "Click",
        "post_delay": 1500
    },
    "乐土刷级-减负模式-点击出击的挑战": {
        "roi": [
            617,
            28,
            221,
            164
        ],
        "recognition": "OCR",
        "expected": [
            "挑战"
        ],
        "action": "Click"
    },
    "乐土刷级-减负模式-点击进入乐土刷级-减负模式": {
        "recognition": "TemplateMatch",
        "template": [
            "周常/往世乐土/导航/往世乐土入口.png"
        ],
        "action": "Click"
    },
    "乐土刷级-减负模式-已进入往世乐土箱庭": {
        "roi": [
            1142,
            189,
            131,
            280
        ],
        "recognition": "OCR",
        "expected": [
            "命定的歧路",
            "装甲强化",
            "追忆之皿"
        ],
        "next": [
            "乐土刷级-减负模式-已进入深层序列选buff准备出击界面",
            "[JumpBack]乐土刷级-减负模式-点击选择深层序列",
            "[JumpBack]乐土刷级-减负模式-打开快速出击",
            "[JumpBack]点击空白位置关闭"
        ]
    },
    "乐土刷级-减负模式-打开快速出击": {
        "roi": [
            1085,
            552,
            182,
            167
        ],
        "recognition": "OCR",
        "expected": [
            "快速出击"
        ],
        // "action": "Click"
        "action": "ClickKey",
        "key": [
            70
        ]
    },
    "乐土刷级-减负模式-点击选择深层序列": {
        "roi": [
            797,
            48,
            367,
            208
        ],
        "recognition": "OCR",
        "expected": [
            "深层序列"
        ],
        "action": "Click"
    },
    "乐土刷级-减负模式-已进入深层序列选buff准备出击界面": {
        "roi": [
            132,
            509,
            329,
            133
        ],
        "recognition": "TemplateMatch",
        "template": [
            "周常/往世乐土/导航/已进入乐土深层序列.png"
        ],
        "next": [
            "乐土刷级-减负模式-已进入女武神选择界面",
            "[JumpBack]乐土刷级-减负模式-未选择任何增益buff提示",
            "[JumpBack]乐土刷级-减负模式-点击进入女武神选择界面"
        ]
    },
    "乐土刷级-减负模式-已进入女武神选择界面": {
        "roi": [
            61,
            134,
            511,
            67
        ],
        "recognition": "OCR",
        "expected": [
            "出战位",
            "支援位"
        ],
        "next": [
            "乐土刷级-减负模式-刻印选择",
            "[JumpBack]乐土刷级-减负模式-点击进入战斗",
            "[JumpBack]乐土刷级-减负模式-加载中",
            "[JumpBack]空任务"
        ]
    },
    "乐土刷级-减负模式-点击进入战斗": {
        "roi": [
            1044,
            617,
            173,
            103
        ],
        "recognition": "OCR",
        "expected": [
            "开始战斗"
        ],
        "action": "Click"
    },
    "乐土刷级-减负模式-加载中": {
        "roi": [
            1049,
            625,
            211,
            87
        ],
        "recognition": "OCR",
        "expected": [
            "加载中.*"
        ],
        "post_delay": 1000
    },
    "乐土刷级-减负模式-刻印选择": {
        "roi": [
            482,
            111,
            252,
            91
        ],
        "recognition": "OCR",
        "expected": [
            "请选择英桀的刻印"
        ],
        "next": [
            "乐土刷级-减负模式-刻印选完了",
            "[JumpBack]乐土刷级-减负模式-普通刻印选取",
            "[JumpBack]乐土刷级-减负模式-可同意该刻印",
            "[JumpBack]乐土刷级-减负模式-刻印获取按钮呼出"
        ]
    },
    "乐土刷级-减负模式-刻印获取按钮呼出": {
        "roi": [
            1147,
            142,
            113,
            434
        ],
        "recognition": "OCR",
        "expected": [
            "普通",
            "专属",
            "核心",
            "增幅"
        ],
        "action": "Click",
        "target_offset": [
            -300,
            35,
            0,
            50
        ],
        "post_delay": 1000
    },
    "乐土刷级-减负模式-可同意该刻印": {
        "roi": [
            1005,
            637,
            261,
            72
        ],
        "recognition": "ColorMatch",
        "upper": [
            251,
            206,
            136
        ],
        "lower": [
            251,
            206,
            136
        ],
        "count": 5000,
        "action": "Click"
    },
    "乐土刷级-减负模式-普通刻印选取": {
        "roi": [
            238,
            440,
            825,
            74
        ],
        "recognition": "OCR",
        "expected": [
            "刻印提供.*增益"
        ],
        "action": "Click"
    },
    "乐土刷级-减负模式-刻印选完了": {
        "rate_limit": 0,
        "post_delay": 0,
        "pre_delay": 0,
        "roi": [
            1058,
            619,
            100,
            100
        ],
        "green_mask": true,
        "recognition": "TemplateMatch",
        "template": [
            "战斗相关/战中检查/已经不用再战斗了-PC.png"
        ],
        "next": [
            "乐土刷级-减负模式-伪寻路-到达目的",
            "乐土刷级-减负模式-刻印选择",
            "[JumpBack]乐土刷级-减负模式-普通刻印选取",
            "[JumpBack]乐土刷级-减负模式-可同意该刻印",
            "[JumpBack]乐土刷级-减负模式-刻印获取按钮呼出",
            "[JumpBack]乐土刷级-减负模式-伪寻路-向前移动"
        ]
    },
    "乐土刷级-减负模式-伪寻路-到达目的": {
        "roi": [
            46,
            270,
            132,
            49
        ],
        "recognition": "OCR",
        "expected": [
            "启动传送锚点"
        ],
        "pre_delay": 500,
        "action": "ClickKey",
        "key": [
            82
        ],
        "next": [
            "乐土刷级-减负模式-已进入往世乐土箱庭",
            "乐土刷级-减负模式-伪寻路-到达目的",
            "乐土刷级-减负模式-已进入战斗",
            "乐土刷级-减负模式-刻印选完了"
        ]
    },
    "乐土刷级-减负模式-已进入战斗": { //战斗逻辑接口
        "post_delay": 0,
        "pre_delay": 0,
        "roi": [
            0,
            0,
            143,
            145
        ],
        "recognition": "TemplateMatch",
        "template": [
            "战斗相关/战中检查/战斗中.png"
        ],
        "next": [
            "乐土刷级-减负模式-战斗结束等待剧情或刻印",
            "减负模式刷-乱打战斗逻辑-战中",
            "乐土刷级-减负模式-失败",
            "乐土刷级-减负模式-可同意该刻印-战后版",
            "乐土刷级-减负模式-BOSS打完选刻印",
            "乐土刷级-减负模式-BOSS打完进剧情"
        ]
    },
    "乐土刷级-减负模式-失败": {
        "roi": [
            307,
            165,
            348,
            126
        ],
        "recognition": "OCR",
        "expected": [
            "战斗失败"
        ],
        "action": "Click",
        "post_delay": 1000,
        "next": [
            "成功进入游戏主菜单",
            "乐土刷级-减负模式-失败",
            "[JumpBack]家园处-点击返回",
            "[JumpBack]点击叉叉",
            "[JumpBack]点击返回主菜单",
            "[JumpBack]输入键码-ESC",
            "[JumpBack]空任务"
        ],
        "focus": {
            "succeeded": "战斗失败，返回主菜单并提前结束任务"
        }
    },
    "乐土刷级-减负模式-战斗结束等待剧情或刻印": {
        "rate_limit": 0,
        "post_delay": 5000,
        "pre_delay": 0,
        "roi": [
            1058,
            619,
            100,
            100
        ],
        "green_mask": true,
        "recognition": "TemplateMatch",
        "template": [
            "战斗相关/战中检查/已经不用再战斗了-PC.png"
        ],
        "next": [
            "乐土刷级-减负模式-BOSS打完选刻印",
            "乐土刷级-减负模式-BOSS打完进剧情",
            "乐土刷级-减负模式-回到战场准备退出",
            "[JumpBack]空任务"
        ]
    },
    "乐土刷级-减负模式-回到战场准备退出": {
        "rate_limit": 0,
        "post_delay": 0,
        "pre_delay": 0,
        "roi": [
            1058,
            619,
            100,
            100
        ],
        "green_mask": true,
        "recognition": "TemplateMatch",
        "template": [
            "战斗相关/战中检查/已经不用再战斗了-PC.png"
        ],
        "next": [
            "乐土刷级-减负模式-已进入往世乐土箱庭-次数结束",
            "乐土刷级-减负模式-已进入往世乐土箱庭",
            "乐土刷级-减负模式-总任务层",
            "[JumpBack]乐土刷级-通用-战斗失败",
            "[JumpBack]乐土刷级-减负模式-放弃并结算确认",
            "[JumpBack]乐土刷级-减负模式-点击放弃并结算",
            "[JumpBack]乐土刷级-战斗结束了-pc专属在战斗界面输入键码ESC点击放弃",
            "[JumpBack]点击空白位置关闭"
        ]
    },
    "乐土刷级-减负模式-已进入往世乐土箱庭-次数结束": {
        "roi": [
            1142,
            189,
            131,
            280
        ],
        "recognition": "OCR",
        "expected": [
            "命定的歧路",
            "装甲强化",
            "追忆之皿"
        ],
        "action": "StopTask"
    },
    "乐土刷级-战斗结束了-pc专属在战斗界面输入键码ESC点击放弃": {
        "pre_delay": 0,
        "roi": [
            0,
            0,
            143,
            145
        ],
        "recognition": "TemplateMatch",
        "template": [
            "战斗相关/战中检查/战斗中.png"
        ],
        "action": "ClickKey",
        "key": 27,
        "post_delay": 500
    },
    "乐土刷级-通用-战斗失败": {
        "roi": [
            307,
            165,
            348,
            126
        ],
        "recognition": "OCR",
        "expected": [
            "战斗失败"
        ],
        "action": "Click"
    },
    "乐土刷级-减负模式-点击放弃并结算": {
        "roi": [
            315,
            600,
            228,
            112
        ],
        "recognition": "OCR",
        "expected": [
            "放弃并结算"
        ],
        "action": "Click",
        "post_delay": 1000
    },
    "乐土刷级-减负模式-放弃并结算确认": {
        "roi": [
            516,
            138,
            247,
            100
        ],
        "recognition": "OCR",
        "expected": [
            "放弃并结算"
        ],
        "action": "Click",
        "target": [
            425,
            492,
            81,
            34
        ],
        "post_delay": 1000
    },
    "乐土刷级-减负模式-可同意该刻印-战后版": {
        "roi": [
            1005,
            637,
            261,
            72
        ],
        "recognition": "ColorMatch",
        "upper": [
            251,
            206,
            136
        ],
        "lower": [
            251,
            206,
            136
        ],
        "count": 5000,
        "action": "Click",
        "next": [
            "乐土刷级-减负模式-已进入战斗",
            "乐土刷级-减负模式-回到战场准备退出",
            "乐土刷级-减负模式-可同意该刻印-战后版",
            "乐土刷级-减负模式-BOSS打完选刻印",
            "乐土刷级-减负模式-BOSS打完进剧情"
        ]
    },
    "减负模式刷-乱打战斗逻辑-战中": {
        "post_delay": 0,
        "pre_delay": 0,
        "rate_limit": 0,
        "roi": [
            0,
            54,
            83,
            150
        ],
        "recognition": "TemplateMatch",
        "green_mask": true,
        "template": [
            "周期性任务/超弦空间/超弦空间-战斗中.png"
        ],
        "action": "ClickKey",
        "key": [
            49, //支援位1
            50, //支援位2
            84, //英桀助战T
            81, //大招Q
            69, //武器技
            70, //星之环F
            74 //普攻
        ],
        "next": [
            "乐土刷级-减负模式-战斗结束等待剧情或刻印",
            "乐土刷级-减负模式-已进入战斗",
            "减负模式刷-乱打战斗逻辑-战中",
            "乐土刷级-减负模式-可同意该刻印-战后版",
            "乐土刷级-减负模式-BOSS打完选刻印",
            "乐土刷级-减负模式-BOSS打完进剧情",
            "[JumpBack]空任务"
        ]
    },
    // "减负模式刷-乱打战斗逻辑-战中-接个平A": {
    //     "rate_limit": 0,
    //     "post_delay": 0,
    //     "pre_delay": 0,
    //     "action": "Click",
    //     "target": [
    //         1186,
    //         634,
    //         32,
    //         30
    //     ],
    //     "next": [
    //         "乐土刷级-减负模式-战斗结束等待剧情或刻印",
    //         "乐土刷级-减负模式-已进入战斗",
    //         "减负模式刷-乱打战斗逻辑-战中",
    //         "乐土刷级-减负模式-可同意该刻印-战后版",
    //         "乐土刷级-减负模式-BOSS打完选刻印",
    //         "乐土刷级-减负模式-BOSS打完进剧情",
    //         "[JumpBack]空任务"
    //     ]
    // },
    "乐土刷级-减负模式-BOSS打完选刻印": {
        "roi": [
            641,
            83,
            138,
            71
        ],
        "recognition": "OCR",
        "expected": [
            ".*刻印"
        ],
        "action": "Click",
        "target": [
            941,
            223,
            147,
            42
        ],
        "next": [
            "乐土刷级-减负模式-回到战场准备退出",
            "乐土刷级-减负模式-可同意该刻印-战后版",
            "乐土刷级-减负模式-BOSS打完选刻印",
            "乐土刷级-减负模式-BOSS打完进剧情"
        ]
    },
    "乐土刷级-减负模式-BOSS打完进剧情": {
        "roi": [
            168,
            12,
            138,
            58
        ],
        "recognition": "OCR",
        "expected": [
            "历史"
        ],
        "action": "Click",
        "target": [
            825,
            547,
            124,
            88
        ],
        "next": [
            "乐土刷级-减负模式-回到战场准备退出",
            "乐土刷级-减负模式-可同意该刻印-战后版",
            "乐土刷级-减负模式-BOSS打完选刻印",
            "乐土刷级-减负模式-BOSS打完进剧情"
        ]
    },
    "乐土刷级-减负模式-伪寻路-向前移动": {
        "roi": [
            46,
            270,
            132,
            49
        ],
        "recognition": "OCR",
        "expected": [
            "启动传送锚点"
        ],
        "inverse": true,
        "action": "ClickKey",
        "key": [
            87
        ],
        "post_delay": 2000
    },
    "乐土刷级-减负模式-点击进入女武神选择界面": {
        "roi": [
            817,
            519,
            228,
            107
        ],
        "recognition": "OCR",
        "expected": [
            "减负战斗"
        ],
        "action": "Click"
    },
    "乐土刷级-减负模式-未选择任何增益buff提示": {
        "roi": [
            521,
            125,
            51,
            392
        ],
        "recognition": "TemplateMatch",
        "template": [
            "周常/往世乐土/刷装甲等级/请选择增益效果.png"
        ],
        "green_mask": true,
        "action": "Click",
        "target": [
            1174,
            124,
            28,
            382
        ],
        "next": [
            "乐土刷级-减负模式-未选择任何增益buff提示-二次点击"
        ]
    },
    "乐土刷级-减负模式-未选择任何增益buff提示-二次点击": {
        "action": "Click",
        "target": [
            1174,
            124,
            28,
            382
        ]
    }
}